adbescapes/README.MD
adbescapes/__init__.py
adbescapes/requirements.txt
adbescapes/thirdparty.json
adbescapes-0.10.dist-info/LICENSE.rst
adbescapes-0.10.dist-info/METADATA
adbescapes-0.10.dist-info/WHEEL
adbescapes-0.10.dist-info/top_level.txt
adbescapes-0.10.dist-info/RECORD
